tpu/systolic_array/mac.sv
module mac #(
    parameter DATA_WIDTH = 8,
    parameter ACC_WIDTH  = 32
) (
    input logic clk,
    input logic rst_n,

    input  logic [DATA_WIDTH-1:0] data_in,   // Activation data input
    output logic [DATA_WIDTH-1:0] data_out,  // Activation data output
    input  logic [ ACC_WIDTH-1:0] acc_in,    // Accumulation input
    output logic [ ACC_WIDTH-1:0] acc_out,   // Accumulation output

    input mac_pkg::mac_ctrl_t ctrl  // Control signal
);
  import mac_pkg::*;

  logic [DATA_WIDTH-1:0] weight;

  always_ff @(posedge clk or negedge rst_n) begin
    if (~rst_n) begin
      data_out <= 0;
      acc_out  <= 0;
      weight   <= 0;
    end else if (ctrl == MAC_CTRL_CLR) begin
      data_out <= 0;
      acc_out  <= 0;
    end else if (ctrl == MAC_CTRL_RUN) begin
      acc_out  <= weight * data_in + acc_in;
      data_out <= data_in;
    end else if (ctrl == MAC_CTRL_LOAD_WEIGHT) begin
      weight   <= data_in;
      data_out <= data_in;
    end
  end
endmodule

tpu/systolic_array/mmu.sv
module mmu #(
    parameter SIZE = 2,
    parameter DATA_WIDTH = 8,
    parameter ACC_WIDTH = 32
) (
    input logic clk,
    input logic rst_n,

    input  logic [DATA_WIDTH-1:0] data_in[SIZE],  // Activation inputs
    output logic [ ACC_WIDTH-1:0] acc_out[SIZE],  // Accumulated outputs

    input mac_pkg::mac_ctrl_t ctrl  // Control signal
);
  logic [DATA_WIDTH-1:0] mac_data_out[SIZE][SIZE];
  logic [ ACC_WIDTH-1:0] mac_acc_out [SIZE][SIZE];

  genvar row;
  genvar col;

  generate
    for (row = 0; row < SIZE; row++) begin
      for (col = 0; col < SIZE; col++) begin
        mac mac_unit (
            .clk(clk),
            .rst_n(rst_n),
            .data_in(col == 0 ? data_in[row] : mac_data_out[row][col-1]),
            .data_out(mac_data_out[row][col]),
            .acc_in(row == 0 ? 0 : mac_acc_out[row-1][col]),
            .acc_out(mac_acc_out[row][col]),
            .ctrl(ctrl)
        );
      end
    end
  endgenerate

  generate
    for (col = 0; col < SIZE; col++) begin
      assign acc_out[col] = mac_acc_out[SIZE-1][col];
    end
  endgenerate

endmodule

tpu/systolic_array/mmu.vcd
$version Generated by VerilatedVcd $end
$timescale 1s $end
 $scope module TOP $end
  $var wire 1 ; clk $end
  $var wire 1 < rst_n $end
  $var wire 8 = data_in[0] [7:0] $end
  $var wire 8 > data_in[1] [7:0] $end
  $var wire 32 ? acc_out[0] [31:0] $end
  $var wire 32 @ acc_out[1] [31:0] $end
  $var wire 2 A ctrl [1:0] $end
  $scope module mmu $end
   $var wire 32 D SIZE [31:0] $end
   $var wire 32 E DATA_WIDTH [31:0] $end
   $var wire 32 F ACC_WIDTH [31:0] $end
   $var wire 1 ; clk $end
   $var wire 1 < rst_n $end
   $var wire 8 = data_in[0] [7:0] $end
   $var wire 8 > data_in[1] [7:0] $end
   $var wire 32 ? acc_out[0] [31:0] $end
   $var wire 32 @ acc_out[1] [31:0] $end
   $var wire 2 A ctrl [1:0] $end
   $var wire 8 # mac_data_out[0][0] [7:0] $end
   $var wire 8 $ mac_data_out[0][1] [7:0] $end
   $var wire 8 % mac_data_out[1][0] [7:0] $end
   $var wire 8 & mac_data_out[1][1] [7:0] $end
   $var wire 32 ' mac_acc_out[0][0] [31:0] $end
   $var wire 32 ( mac_acc_out[0][1] [31:0] $end
   $var wire 32 ) mac_acc_out[1][0] [31:0] $end
   $var wire 32 * mac_acc_out[1][1] [31:0] $end
   $scope module genblk1[0] $end
    $scope module genblk1[0] $end
     $scope module mac_unit $end
      $var wire 32 E DATA_WIDTH [31:0] $end
      $var wire 32 F ACC_WIDTH [31:0] $end
      $var wire 1 ; clk $end
      $var wire 1 < rst_n $end
      $var wire 8 B data_in [7:0] $end
      $var wire 8 + data_out [7:0] $end
      $var wire 32 G acc_in [31:0] $end
      $var wire 32 , acc_out [31:0] $end
      $var wire 2 A ctrl [1:0] $end
      $var wire 8 - weight [7:0] $end
     $upscope $end
    $upscope $end
    $scope module genblk1[1] $end
     $scope module mac_unit $end
      $var wire 32 E DATA_WIDTH [31:0] $end
      $var wire 32 F ACC_WIDTH [31:0] $end
      $var wire 1 ; clk $end
      $var wire 1 < rst_n $end
      $var wire 8 . data_in [7:0] $end
      $var wire 8 / data_out [7:0] $end
      $var wire 32 G acc_in [31:0] $end
      $var wire 32 0 acc_out [31:0] $end
      $var wire 2 A ctrl [1:0] $end
      $var wire 8 1 weight [7:0] $end
     $upscope $end
    $upscope $end
   $upscope $end
   $scope module genblk1[1] $end
    $scope module genblk1[0] $end
     $scope module mac_unit $end
      $var wire 32 E DATA_WIDTH [31:0] $end
      $var wire 32 F ACC_WIDTH [31:0] $end
      $var wire 1 ; clk $end
      $var wire 1 < rst_n $end
      $var wire 8 C data_in [7:0] $end
      $var wire 8 2 data_out [7:0] $end
      $var wire 32 3 acc_in [31:0] $end
      $var wire 32 4 acc_out [31:0] $end
      $var wire 2 A ctrl [1:0] $end
      $var wire 8 5 weight [7:0] $end
     $upscope $end
    $upscope $end
    $scope module genblk1[1] $end
     $scope module mac_unit $end
      $var wire 32 E DATA_WIDTH [31:0] $end
      $var wire 32 F ACC_WIDTH [31:0] $end
      $var wire 1 ; clk $end
      $var wire 1 < rst_n $end
      $var wire 8 6 data_in [7:0] $end
      $var wire 8 7 data_out [7:0] $end
      $var wire 32 8 acc_in [31:0] $end
      $var wire 32 9 acc_out [31:0] $end
      $var wire 2 A ctrl [1:0] $end
      $var wire 8 : weight [7:0] $end
     $upscope $end
    $upscope $end
   $upscope $end
  $upscope $end
 $upscope $end
$enddefinitions $end


#10
b00000000 #
b00000000 $
b00000000 %
b00000000 &
b00000000000000000000000000000000 '
b00000000000000000000000000000000 (
b00000000000000000000000000000000 )
b00000000000000000000000000000000 *
b00000000 +
b00000000000000000000000000000000 ,
b00000000 -
b00000000 .
b00000000 /
b00000000000000000000000000000000 0
b00000000 1
b00000000 2
b00000000000000000000000000000000 3
b00000000000000000000000000000000 4
b00000000 5
b00000000 6
b00000000 7
b00000000000000000000000000000000 8
b00000000000000000000000000000000 9
b00000000 :
0;
0<
b00000000 =
b00000000 >
b00000000000000000000000000000000 ?
b00000000000000000000000000000000 @
b00 A
b00000000 B
b00000000 C
b00000000000000000000000000000010 D
b00000000000000000000000000001000 E
b00000000000000000000000000100000 F
b00000000000000000000000000000000 G
#20
1<
#30
#40
1;
#50
0;
b00000010 =
b00000100 >
b10 A
b00000010 B
b00000100 C
#60
b00000010 #
b00000100 %
b00000010 +
b00000010 -
b00000010 .
b00000100 2
b00000100 5
b00000100 6
1;
#70
0;
b00000001 =
b00000011 >
b00000001 B
b00000011 C
#80
b00000001 #
b00000010 $
b00000011 %
b00000100 &
b00000001 +
b00000001 -
b00000001 .
b00000010 /
b00000010 1
b00000011 2
b00000011 5
b00000011 6
b00000100 7
b00000100 :
1;
#90
0;
b00 A
#100
b00000000 #
b00000000 $
b00000000 %
b00000000 &
b00000000 +
b00000000 .
b00000000 /
b00000000 2
b00000000 6
b00000000 7
1;
#110
0;
b00000000 =
b00000101 >
b01 A
b00000000 B
b00000101 C
#120
b00000101 %
b00000000000000000000000000001111 )
b00000101 2
b00000000000000000000000000001111 4
b00000101 6
1;
b00000000000000000000000000001111 ?
#130
0;
#140
b00000101 &
b00000000000000000000000000010100 *
b00000101 7
b00000000000000000000000000010100 9
1;
b00000000000000000000000000010100 @
